{
  "id": "",
  "name": "",
  "font_family": "iconfont",
  "css_prefix_text": "icon-",
  "description": "",
  "glyphs": [
    {
      "icon_id": "15838424",
      "name": "add",
      "font_class": "add",
      "unicode": "e664",
      "unicode_decimal": 58980
    },
    {
      "icon_id": "15838432",
      "name": "browse",
      "font_class": "browse",
      "unicode": "e666",
      "unicode_decimal": 58982
    },
    {
      "icon_id": "15838508",
      "name": "more",
      "font_class": "more",
      "unicode": "e679",
      "unicode_decimal": 59001
    },
    {
      "icon_id": "15838547",
      "name": "user",
      "font_class": "user",
      "unicode": "e682",
      "unicode_decimal": 59010
    }
  ]
}
